omicfate/__init__.py
omicfate/_omicfate.py
omicfate-0.0.1.dist-info/LICENSE
omicfate-0.0.1.dist-info/WHEEL
omicfate-0.0.1.dist-info/METADATA
omicfate-0.0.1.dist-info/RECORD
