Metadata-Version: 2.1
Name: omicfate
Version: 0.0.1
Summary: OmicFate: Unraveling the Secrets of Cellular Fate Determination
Keywords: bioinformatics,deep-learning,scRNA-seq,RNA-seq
Author-email: Zehua Zeng <starlitnightly@gmail.com>
Requires-Python: >=3.8
Classifier: Intended Audience :: Science/Research
Classifier: Natural Language :: English
Classifier: Operating System :: MacOS :: MacOS X
Classifier: Operating System :: POSIX :: Linux
Classifier: Programming Language :: Python :: 3
Classifier: Programming Language :: Python :: 3.8
Classifier: Programming Language :: Python :: 3.9
Classifier: Topic :: Scientific/Engineering :: Bio-Informatics
Requires-Dist: numpy>=1.22, <1.24
Requires-Dist: scanpy>=1.9
Requires-Dist: pandas>=1.0.3, <=1.5.3
Requires-Dist: matplotlib<3.7
Requires-Dist: scikit-learn>=1.2
Requires-Dist: scipy>=1.8, <1.12
Requires-Dist: seaborn>=0.11
Requires-Dist: scikit-misc>=0.1
Requires-Dist: palantir
Project-URL: Github, https://github.com/Starlitnightly/omicfate
